_pyngraph.cpython-38-x86_64-linux-gnu.so
ngraph/__init__.py
ngraph/exceptions.py
ngraph/helpers.py
ngraph/opset_utils.py
ngraph/impl/__init__.py
ngraph/impl/op/__init__.py
ngraph/impl/op/util/__init__.py
ngraph/impl/passes/__init__.py
ngraph/opset1/__init__.py
ngraph/opset1/ops.py
ngraph/opset2/__init__.py
ngraph/opset2/ops.py
ngraph/opset3/__init__.py
ngraph/opset3/ops.py
ngraph/opset4/__init__.py
ngraph/opset4/ops.py
ngraph/opset5/__init__.py
ngraph/opset5/ops.py
ngraph/utils/__init__.py
ngraph/utils/broadcasting.py
ngraph/utils/decorators.py
ngraph/utils/input_validation.py
ngraph/utils/node_factory.py
ngraph/utils/reduction.py
ngraph/utils/tensor_iterator_types.py
ngraph/utils/types.py
openvino/__init__.py
openvino/inference_engine/__init__.py
openvino/inference_engine/constants.cpython-38-x86_64-linux-gnu.so
openvino/inference_engine/ie_api.cpython-38-x86_64-linux-gnu.so
openvino_ubuntu20-2021.2-170.data/data/lib/cache.json
openvino_ubuntu20-2021.2-170.data/data/lib/libHeteroPlugin.so
openvino_ubuntu20-2021.2-170.data/data/lib/libMKLDNNPlugin.so
openvino_ubuntu20-2021.2-170.data/data/lib/libMultiDevicePlugin.so
openvino_ubuntu20-2021.2-170.data/data/lib/libclDNNPlugin.so
openvino_ubuntu20-2021.2-170.data/data/lib/libinference_engine.so
openvino_ubuntu20-2021.2-170.data/data/lib/libinference_engine_c_api.so
openvino_ubuntu20-2021.2-170.data/data/lib/libinference_engine_ir_reader.so
openvino_ubuntu20-2021.2-170.data/data/lib/libinference_engine_legacy.so
openvino_ubuntu20-2021.2-170.data/data/lib/libinference_engine_lp_transformations.so
openvino_ubuntu20-2021.2-170.data/data/lib/libinference_engine_onnx_reader.so
openvino_ubuntu20-2021.2-170.data/data/lib/libinference_engine_preproc.so
openvino_ubuntu20-2021.2-170.data/data/lib/libinference_engine_transformations.so
openvino_ubuntu20-2021.2-170.data/data/lib/libmyriadPlugin.so
openvino_ubuntu20-2021.2-170.data/data/lib/libngraph.so
openvino_ubuntu20-2021.2-170.data/data/lib/libonnx_importer.so
openvino_ubuntu20-2021.2.dist-info/METADATA
openvino_ubuntu20-2021.2.dist-info/WHEEL
openvino_ubuntu20-2021.2.dist-info/top_level.txt
openvino_ubuntu20-2021.2.dist-info/RECORD
