Metadata-Version: 2.1
Name: openvino-ubuntu20
Version: 2021.2
Summary: Inference Engine Python* API
Home-page: UNKNOWN
Author: Intel Corporation
Author-email: openvino_pushbot@intel.com
License: Proprietary - Intel
Platform: UNKNOWN
Requires-Dist: tbb (==2020.3.254)
Requires-Dist: numpy (>=1.16.3)
